{
  "main": {
    "id": "166e71090555c879",
    "type": "split",
    "children": [
      {
        "id": "a8994f3d5ff673f6",
        "type": "tabs",
        "children": [
          {
            "id": "2cceb1c7eda0575e",
            "type": "leaf",
            "state": {
              "type": "markdown",
              "state": {
                "file": "AST/Cross-site request forgery (CSRF).md",
                "mode": "source",
                "source": false
              },
              "icon": "lucide-file",
              "title": "Cross-site request forgery (CSRF)"
            }
          },
          {
            "id": "3b2597b48e07c129",
            "type": "leaf",
            "state": {
              "type": "markdown",
              "state": {
                "file": "AST/In-band SQL Injection.md",
                "mode": "source",
                "source": false
              },
              "icon": "lucide-file",
              "title": "In-band SQL Injection"
            }
          },
          {
            "id": "794bc1d1e8b3b1d1",
            "type": "leaf",
            "state": {
              "type": "markdown",
              "state": {
                "file": "AST/Blind SQL Injection.md",
                "mode": "source",
                "source": false
              },
              "icon": "lucide-file",
              "title": "Blind SQL Injection"
            }
          },
          {
            "id": "cf7d97ef6099a4ee",
            "type": "leaf",
            "state": {
              "type": "markdown",
              "state": {
                "file": "_REMA_UNIT_5.md",
                "mode": "source",
                "source": false
              },
              "icon": "lucide-file",
              "title": "_REMA_UNIT_5"
            }
          }
        ]
      }
    ],
    "direction": "vertical"
  },
  "left": {
    "id": "96a4a5648acb1162",
    "type": "split",
    "children": [
      {
        "id": "410519eab3b04170",
        "type": "tabs",
        "children": [
          {
            "id": "413229dc452c5cc8",
            "type": "leaf",
            "state": {
              "type": "file-explorer",
              "state": {
                "sortOrder": "alphabetical",
                "autoReveal": false
              },
              "icon": "lucide-folder-closed",
              "title": "Files"
            }
          },
          {
            "id": "7f793b087f36370d",
            "type": "leaf",
            "state": {
              "type": "search",
              "state": {
                "query": "",
                "matchingCase": false,
                "explainSearch": false,
                "collapseAll": false,
                "extraContext": false,
                "sortOrder": "alphabetical"
              },
              "icon": "lucide-search",
              "title": "Search"
            }
          },
          {
            "id": "57d86253de79235c",
            "type": "leaf",
            "state": {
              "type": "bookmarks",
              "state": {},
              "icon": "lucide-bookmark",
              "title": "Bookmarks"
            }
          }
        ]
      }
    ],
    "direction": "horizontal",
    "width": 300
  },
  "right": {
    "id": "2aafc5d1059ce854",
    "type": "split",
    "children": [
      {
        "id": "f96dc8fb4e00289b",
        "type": "tabs",
        "children": [
          {
            "id": "9e02fa04231c849d",
            "type": "leaf",
            "state": {
              "type": "backlink",
              "state": {
                "file": "_AST_UNIT 3.md",
                "collapseAll": false,
                "extraContext": false,
                "sortOrder": "alphabetical",
                "showSearch": false,
                "searchQuery": "",
                "backlinkCollapsed": false,
                "unlinkedCollapsed": true
              },
              "icon": "links-coming-in",
              "title": "Backlinks for _AST_UNIT 3"
            }
          },
          {
            "id": "3ce9788993d35afe",
            "type": "leaf",
            "state": {
              "type": "outgoing-link",
              "state": {
                "file": "_AST_UNIT 3.md",
                "linksCollapsed": false,
                "unlinkedCollapsed": true
              },
              "icon": "links-going-out",
              "title": "Outgoing links from _AST_UNIT 3"
            }
          },
          {
            "id": "65e86176b6f47402",
            "type": "leaf",
            "state": {
              "type": "tag",
              "state": {
                "sortOrder": "frequency",
                "useHierarchy": true,
                "showSearch": false,
                "searchQuery": ""
              },
              "icon": "lucide-tags",
              "title": "Tags"
            }
          },
          {
            "id": "546a5572704b1295",
            "type": "leaf",
            "state": {
              "type": "all-properties",
              "state": {
                "sortOrder": "frequency",
                "showSearch": false,
                "searchQuery": ""
              },
              "icon": "lucide-archive",
              "title": "All properties"
            }
          },
          {
            "id": "8617261ec82f24b4",
            "type": "leaf",
            "state": {
              "type": "outline",
              "state": {
                "file": "_AST_UNIT 3.md",
                "followCursor": false,
                "showSearch": false,
                "searchQuery": ""
              },
              "icon": "lucide-list",
              "title": "Outline of _AST_UNIT 3"
            }
          }
        ]
      }
    ],
    "direction": "horizontal",
    "width": 300,
    "collapsed": true
  },
  "left-ribbon": {
    "hiddenItems": {
      "switcher:Open quick switcher": false,
      "graph:Open graph view": false,
      "canvas:Create new canvas": false,
      "daily-notes:Open today's daily note": false,
      "templates:Insert template": false,
      "command-palette:Open command palette": false,
      "bases:Create new base": false
    }
  },
  "active": "413229dc452c5cc8",
  "lastOpenFiles": [
    "AST/HTTP request smuggling.md",
    "AST/_AST_LABS.md",
    "_REMA_UNIT_5.md",
    "AST/Blind SQL Injection.md",
    "AST/In-band SQL Injection.md",
    "AST/Cross-site request forgery (CSRF).md",
    "AST/__AST.md",
    "AST/_AST_UNIT_1.md",
    "AST/Server-side request forgery (SSRF).md",
    "AST/_AST_UNIT_5.md",
    "AST/_AST_UNIT_4.md",
    "AST/_AST_UNIT_3.md",
    "AST/_AST_UNIT_2.md",
    "AST",
    "_AST_LABS.md",
    "AST.md",
    "AST/Pasted image 20260427180144.png",
    "AST/Pasted image 20260427150702.png",
    "_AST_UNIT_1.md",
    "_AST_UNIT_2.md",
    "_AST_UNIT_3.md",
    "_AST_UNIT_4.md",
    "_AST_UNIT_5.md",
    "_REMA_UNIT_3.md",
    "REMA.md",
    "_REMA_UNIT 4.md",
    "_REMA_UNIT 3.md",
    "DFIR.md",
    "VAPT.md",
    "Pasted image 20260406103700.png",
    "Pasted image 20260406102705.png",
    "Pasted image 20260406101913.png"
  ]
}